README.md
setup.py
mbSTATS/__init__.py
mbSTATS/data_preparation.py
mbSTATS/final_df_prep.py
mbSTATS/pval_calculation.py
mbSTATS/pval_plot.py
mbSTATS.egg-info/PKG-INFO
mbSTATS.egg-info/SOURCES.txt
mbSTATS.egg-info/dependency_links.txt
mbSTATS.egg-info/requires.txt
mbSTATS.egg-info/top_level.txt